{"version":3,"kind":"Article","sha256":"f1cccd65f9a5b0d538bd9b5fe2ed57b280d54404f38fc725dfd60253432c1381","slug":"index","location":"/index.md","dependencies":[],"frontmatter":{"title":"Home","content_includes_title":false,"exports":[{"format":"md","filename":"index.md","url":"Luminescent.jl/build/index-6c28d50ece9603f61e7a7b11394e0a8f.md"}]},"mdast":{"type":"root","children":[{"type":"block","children":[{"type":"heading","depth":2,"position":{"start":{"line":2,"column":1},"end":{"line":2,"column":1}},"children":[{"type":"text","value":"Overview","position":{"start":{"line":2,"column":1},"end":{"line":2,"column":1}},"key":"ykQqs7whMJ"}],"identifier":"overview","label":"Overview","html_id":"overview","implicit":true,"key":"IfwjDMkWbQ"},{"type":"paragraph","position":{"start":{"line":3,"column":1},"end":{"line":3,"column":1}},"children":[{"type":"link","url":"https://luminescentai.com","position":{"start":{"line":3,"column":1},"end":{"line":3,"column":1}},"children":[{"type":"text","value":"Luminescent AI","position":{"start":{"line":3,"column":1},"end":{"line":3,"column":1}},"key":"tK6tICG3Pm"}],"urlSource":"https://luminescentai.com","key":"ushkQXsjtE"},{"type":"text","value":" harnesses physics grounded AI for designing electromagnetic structures in photonics and RF. We offer Lumi FDTD for full wave simulations and inverse design, and Lumi Photonic PDK of inverse designed photonic components.","position":{"start":{"line":3,"column":1},"end":{"line":3,"column":1}},"key":"aNBUAo9RVp"}],"key":"frOWh1rCan"},{"type":"heading","depth":2,"position":{"start":{"line":4,"column":1},"end":{"line":4,"column":1}},"children":[{"type":"text","value":"Aboout","position":{"start":{"line":4,"column":1},"end":{"line":4,"column":1}},"key":"MOv8V8ry4v"}],"identifier":"aboout","label":"Aboout","html_id":"aboout","implicit":true,"key":"hwzh30TKSN"},{"type":"paragraph","position":{"start":{"line":5,"column":1},"end":{"line":5,"column":1}},"children":[{"type":"text","value":"We’re Stanford alum and founded Luminescent AI in 2025 to democratize photonic and RF design with AI.","position":{"start":{"line":5,"column":1},"end":{"line":5,"column":1}},"key":"FCymluLmyh"}],"key":"innQRxhdHK"},{"type":"paragraph","position":{"start":{"line":7,"column":1},"end":{"line":10,"column":1}},"children":[{"type":"link","url":"https://www.linkedin.com/company/luminescent-ai","position":{"start":{"line":7,"column":1},"end":{"line":7,"column":1}},"children":[{"type":"text","value":"LinkedIn","position":{"start":{"line":7,"column":1},"end":{"line":7,"column":1}},"key":"f62VkFTjfZ"}],"urlSource":"https://www.linkedin.com/company/luminescent-ai","key":"vpRo62Y5vB"},{"type":"text","value":": follow us for updates and opportunities!","position":{"start":{"line":7,"column":1},"end":{"line":7,"column":1}},"key":"WGrix61KH8"},{"type":"break","position":{"start":{"line":7,"column":1},"end":{"line":7,"column":1}},"key":"mpT1G5vtAU"},{"type":"link","url":"https://luminescentai.com","position":{"start":{"line":7,"column":1},"end":{"line":7,"column":1}},"children":[{"type":"text","value":"Website","position":{"start":{"line":7,"column":1},"end":{"line":7,"column":1}},"key":"letpRxpCtq"}],"urlSource":"https://luminescentai.com","key":"w76bNTC7wr"},{"type":"text","value":"\nEmail: ","position":{"start":{"line":7,"column":1},"end":{"line":7,"column":1}},"key":"KxRAi0q474"},{"type":"link","url":"mailto:paul@luminescentai.com","position":{"start":{"line":7,"column":1},"end":{"line":7,"column":1}},"children":[{"type":"text","value":"paul@luminescentai​.com","position":{"start":{"line":7,"column":1},"end":{"line":7,"column":1}},"key":"YeTn9umIaR"}],"urlSource":"mailto:paul@luminescentai.com","key":"xN8qWWxnEW"},{"type":"break","position":{"start":{"line":7,"column":1},"end":{"line":7,"column":1}},"key":"V15ylzavWF"},{"type":"text","value":"WhatsApp and WeChat: +1 (650) 776-7724","position":{"start":{"line":7,"column":1},"end":{"line":7,"column":1}},"key":"fzMHtx4mdV"}],"key":"t3jx0nVSwe"}],"key":"LZVwx45FRU"}],"key":"mvv90hPH7N"},"references":{"cite":{"order":[],"data":{}}},"footer":{"navigation":{"next":{"title":"Features","url":"/features","group":"Lumi FDTD"}}},"domain":"http://localhost:3003"}