{"version":3,"kind":"Article","sha256":"c5ff0ff85f881d947df24e38d9bc95732e2f531d44690b63a0494f10d68d729e","slug":"install","location":"/install.md","dependencies":[],"frontmatter":{"title":"Installation","content_includes_title":false,"numbering":{"title":{"offset":1}},"exports":[{"format":"md","filename":"install.md","url":"/Luminescent.jl/build/install-05e54604ad65885f3e22d3e5d703fabc.md"}]},"mdast":{"type":"root","children":[{"type":"block","children":[{"type":"paragraph","position":{"start":{"line":2,"column":1},"end":{"line":2,"column":1}},"children":[{"type":"text","value":"Please fill out ","position":{"start":{"line":2,"column":1},"end":{"line":2,"column":1}},"key":"qZXxc6gl3W"},{"type":"link","url":"https://forms.gle/fP9wAkdJinT8t66w8","position":{"start":{"line":2,"column":1},"end":{"line":2,"column":1}},"children":[{"type":"text","value":"new user form","position":{"start":{"line":2,"column":1},"end":{"line":2,"column":1}},"key":"KrLDLcO5HY"}],"urlSource":"https://forms.gle/fP9wAkdJinT8t66w8","key":"f5LFt3mlw5"},{"type":"text","value":" to obtain install scripts for unrestricted simulation. Doesn’t include inverse design.","position":{"start":{"line":2,"column":1},"end":{"line":2,"column":1}},"key":"XPNOjSEljp"}],"key":"WLTsqt3PvU"},{"type":"paragraph","position":{"start":{"line":4,"column":1},"end":{"line":4,"column":1}},"children":[{"type":"text","value":"Holiday notice: Luminescent Community Cluster will come online on 01-12","position":{"start":{"line":4,"column":1},"end":{"line":4,"column":1}},"key":"jitDTvTIoX"}],"key":"xvGpJOavR3"},{"type":"heading","depth":2,"position":{"start":{"line":6,"column":1},"end":{"line":6,"column":1}},"children":[{"type":"text","value":"Option 1: Luminescent Community Cluster (free and public)","position":{"start":{"line":6,"column":1},"end":{"line":6,"column":1}},"key":"uceABzgOjV"}],"identifier":"option-1-luminescent-community-cluster-free-and-public","label":"Option 1: Luminescent Community Cluster (free and public)","html_id":"option-1-luminescent-community-cluster-free-and-public","implicit":true,"key":"VYR7TxzEvy"},{"type":"paragraph","position":{"start":{"line":7,"column":1},"end":{"line":7,"column":1}},"children":[{"type":"text","value":"Run on our latest Nvidia Blackwell GPUs for free! Just ","position":{"start":{"line":7,"column":1},"end":{"line":7,"column":1}},"key":"YPbkJiLGz3"},{"type":"link","url":"https://forms.gle/fP9wAkdJinT8t66w8","position":{"start":{"line":7,"column":1},"end":{"line":7,"column":1}},"children":[{"type":"text","value":"register","position":{"start":{"line":7,"column":1},"end":{"line":7,"column":1}},"key":"fDTe8qTVTa"}],"urlSource":"https://forms.gle/fP9wAkdJinT8t66w8","key":"iGriyVVOUs"},{"type":"text","value":" (allow 1 business day for processing) and install our python frontend via ","position":{"start":{"line":7,"column":1},"end":{"line":7,"column":1}},"key":"edsiPfCdTR"},{"type":"inlineCode","value":"pip install luminescent","position":{"start":{"line":7,"column":1},"end":{"line":7,"column":1}},"key":"RoNXeFbD04"},{"type":"text","value":". Then see our simulation tutorials. All your jobs on the community cluster are publicly visible. If you want a private and secured environment, please upgrade to an enterprise cluster.","position":{"start":{"line":7,"column":1},"end":{"line":7,"column":1}},"key":"rglKzwlUrc"}],"key":"fwK9T7R2mK"},{"type":"heading","depth":2,"position":{"start":{"line":9,"column":1},"end":{"line":9,"column":1}},"children":[{"type":"text","value":"Option 2: Luminescent Enterprise Cluster (private and secure)","position":{"start":{"line":9,"column":1},"end":{"line":9,"column":1}},"key":"AtoofAPrTD"}],"identifier":"option-2-luminescent-enterprise-cluster-private-and-secure","label":"Option 2: Luminescent Enterprise Cluster (private and secure)","html_id":"option-2-luminescent-enterprise-cluster-private-and-secure","implicit":true,"key":"HmDVKY4Tj9"},{"type":"paragraph","position":{"start":{"line":10,"column":1},"end":{"line":10,"column":1}},"children":[{"type":"text","value":"Similar to community cluster but private and secured for your organization. Comes with premium support and consulting. Pricing is a fixed annual fee plus $3 per GPU hour (similar to raw rates on GCP or AWS). Sign up via ","position":{"start":{"line":10,"column":1},"end":{"line":10,"column":1}},"key":"XXf4on5HX9"},{"type":"link","url":"mailto:info@luminescentai.com","position":{"start":{"line":10,"column":1},"end":{"line":10,"column":1}},"children":[{"type":"text","value":"info@luminescentai​.com","position":{"start":{"line":10,"column":1},"end":{"line":10,"column":1}},"key":"tzmE5gUJPn"}],"urlSource":"mailto:info@luminescentai.com","key":"NeNj8Q4c7F"}],"key":"XqcxPSUf7z"},{"type":"heading","depth":2,"position":{"start":{"line":12,"column":1},"end":{"line":12,"column":1}},"children":[{"type":"text","value":"Option 3: Local Installation","position":{"start":{"line":12,"column":1},"end":{"line":12,"column":1}},"key":"zT56nYACep"}],"identifier":"option-3-local-installation","label":"Option 3: Local Installation","html_id":"option-3-local-installation","implicit":true,"key":"emGYuNC41Q"},{"type":"paragraph","position":{"start":{"line":13,"column":1},"end":{"line":13,"column":1}},"children":[{"type":"text","value":"Customers of Enterprise Cluster are also entitled to local installation binaries upon request.","position":{"start":{"line":13,"column":1},"end":{"line":13,"column":1}},"key":"GeJFYOCTu5"}],"key":"qaJKpzx5RX"}],"key":"e4UMUxG6Y9"}],"key":"SpdvtNMcl7"},"references":{"cite":{"order":[],"data":{}}},"footer":{"navigation":{"prev":{"title":"Features","url":"/features","group":"Lumi FDTD"},"next":{"title":"Photonic integrated circuit: ring resonator","url":"/test-ring","group":"Simulation tutorials"}}},"domain":"http://localhost:3004"}